pybrica/__init__.py
pybrica/__version__.py
pybrica/circuit.py
pybrica/component.py
pybrica/messager.py
pybrica/ros.py
pybrica/scheduler.py
pybrica-0.0.4.dist-info/METADATA
pybrica-0.0.4.dist-info/RECORD
pybrica-0.0.4.dist-info/WHEEL
pybrica-0.0.4.dist-info/top_level.txt
