Metadata-Version: 2.1
Name: pybrica
Version: 0.0.4
Summary: Python interface for BriCA.
Home-page: https://github.com/wbap/PyBriCA
Author: Kotone Itaya
Author-email: kotone@sfc.keio.ac.jp
License: MIT
Platform: UNKNOWN
Classifier: License :: OSI Approved :: MIT License
Classifier: Programming Language :: Python
Classifier: Programming Language :: Python :: 3
Classifier: Programming Language :: Python :: 3.6
Classifier: Programming Language :: Python :: Implementation :: CPython
Classifier: Programming Language :: Python :: Implementation :: PyPy
Requires-Python: >=3.4.0
Requires-Dist: six
